ineye/__init__.py
ineye/detect.py
ineye/viz.py
ineye-0.0.3.dist-info/LICENSE
ineye-0.0.3.dist-info/METADATA
ineye-0.0.3.dist-info/WHEEL
ineye-0.0.3.dist-info/entry_points.txt
ineye-0.0.3.dist-info/top_level.txt
ineye-0.0.3.dist-info/RECORD
