Metadata-Version: 2.1
Name: ineye
Version: 0.0.3
Summary: Vision data exploration and frame sampling toolkit for videos
Author-email: Rahul Vishwakarma <vishwakarma.rhl@gmail.com>
License: MIT License
Project-URL: Homepage, https://github.com/karmarv/ineye
Keywords: vision,video,processing
Classifier: License :: OSI Approved :: MIT License
Classifier: Programming Language :: Python
Classifier: Programming Language :: Python :: 3
Requires-Python: >=3.8
License-File: LICENSE
Requires-Dist: tqdm
Requires-Dist: opencv-python
Requires-Dist: ffmpeg-python
Requires-Dist: tomli; python_version < "3.11"
Provides-Extra: dev
Requires-Dist: black; extra == "dev"
Requires-Dist: bumpver; extra == "dev"
Requires-Dist: isort; extra == "dev"
Requires-Dist: pip-tools; extra == "dev"
Requires-Dist: pytest; extra == "dev"
